{
  "Ixeh/apps/Ixeh": {
    "root": [
      "Ixeh/apps/Ixeh/eslint.config.mjs",
      "@nx/eslint/plugin"
    ],
    "projectType": [
      "Ixeh/apps/Ixeh/webpack.config.js",
      "@nx/webpack/plugin"
    ],
    "targets": [
      "Ixeh/apps/Ixeh/webpack.config.js",
      "@nx/webpack/plugin"
    ],
    "targets.build": [
      "Ixeh/apps/Ixeh/webpack.config.js",
      "@nx/webpack/plugin"
    ],
    "targets.build.options": [
      "Ixeh/apps/Ixeh/webpack.config.js",
      "@nx/webpack/plugin"
    ],
    "targets.build.cache": [
      "Ixeh/apps/Ixeh/webpack.config.js",
      "@nx/webpack/plugin"
    ],
    "targets.build.dependsOn": [
      "Ixeh/apps/Ixeh/webpack.config.js",
      "@nx/webpack/plugin"
    ],
    "targets.build.inputs": [
      "Ixeh/apps/Ixeh/webpack.config.js",
      "@nx/webpack/plugin"
    ],
    "targets.build.outputs": [
      "Ixeh/apps/Ixeh/webpack.config.js",
      "@nx/webpack/plugin"
    ],
    "targets.build.metadata": [
      "Ixeh/apps/Ixeh/webpack.config.js",
      "@nx/webpack/plugin"
    ],
    "targets.build.executor": [
      "Ixeh/apps/Ixeh/webpack.config.js",
      "@nx/webpack/plugin"
    ],
    "targets.build.options.cwd": [
      "Ixeh/apps/Ixeh/webpack.config.js",
      "@nx/webpack/plugin"
    ],
    "targets.build.options.args": [
      "Ixeh/apps/Ixeh/webpack.config.js",
      "@nx/webpack/plugin"
    ],
    "targets.build.options.command": [
      "Ixeh/apps/Ixeh/webpack.config.js",
      "@nx/webpack/plugin"
    ],
    "targets.build.metadata.technologies": [
      "Ixeh/apps/Ixeh/webpack.config.js",
      "@nx/webpack/plugin"
    ],
    "targets.build.metadata.technologies.0": [
      "Ixeh/apps/Ixeh/webpack.config.js",
      "@nx/webpack/plugin"
    ],
    "targets.build.metadata.description": [
      "Ixeh/apps/Ixeh/webpack.config.js",
      "@nx/webpack/plugin"
    ],
    "targets.build.metadata.help": [
      "Ixeh/apps/Ixeh/webpack.config.js",
      "@nx/webpack/plugin"
    ],
    "targets.build.metadata.help.command": [
      "Ixeh/apps/Ixeh/webpack.config.js",
      "@nx/webpack/plugin"
    ],
    "targets.build.metadata.help.example": [
      "Ixeh/apps/Ixeh/webpack.config.js",
      "@nx/webpack/plugin"
    ],
    "targets.serve": [
      "Ixeh/apps/Ixeh/webpack.config.js",
      "@nx/webpack/plugin"
    ],
    "targets.serve.continuous": [
      "Ixeh/apps/Ixeh/webpack.config.js",
      "@nx/webpack/plugin"
    ],
    "targets.serve.options": [
      "Ixeh/apps/Ixeh/webpack.config.js",
      "@nx/webpack/plugin"
    ],
    "targets.serve.metadata": [
      "Ixeh/apps/Ixeh/webpack.config.js",
      "@nx/webpack/plugin"
    ],
    "targets.serve.executor": [
      "Ixeh/apps/Ixeh/webpack.config.js",
      "@nx/webpack/plugin"
    ],
    "targets.serve.options.cwd": [
      "Ixeh/apps/Ixeh/webpack.config.js",
      "@nx/webpack/plugin"
    ],
    "targets.serve.options.args": [
      "Ixeh/apps/Ixeh/webpack.config.js",
      "@nx/webpack/plugin"
    ],
    "targets.serve.options.command": [
      "Ixeh/apps/Ixeh/webpack.config.js",
      "@nx/webpack/plugin"
    ],
    "targets.serve.metadata.technologies": [
      "Ixeh/apps/Ixeh/webpack.config.js",
      "@nx/webpack/plugin"
    ],
    "targets.serve.metadata.technologies.0": [
      "Ixeh/apps/Ixeh/webpack.config.js",
      "@nx/webpack/plugin"
    ],
    "targets.serve.metadata.description": [
      "Ixeh/apps/Ixeh/webpack.config.js",
      "@nx/webpack/plugin"
    ],
    "targets.serve.metadata.help": [
      "Ixeh/apps/Ixeh/webpack.config.js",
      "@nx/webpack/plugin"
    ],
    "targets.serve.metadata.help.command": [
      "Ixeh/apps/Ixeh/webpack.config.js",
      "@nx/webpack/plugin"
    ],
    "targets.serve.metadata.help.example": [
      "Ixeh/apps/Ixeh/webpack.config.js",
      "@nx/webpack/plugin"
    ],
    "targets.preview": [
      "Ixeh/apps/Ixeh/webpack.config.js",
      "@nx/webpack/plugin"
    ],
    "targets.preview.continuous": [
      "Ixeh/apps/Ixeh/webpack.config.js",
      "@nx/webpack/plugin"
    ],
    "targets.preview.options": [
      "Ixeh/apps/Ixeh/webpack.config.js",
      "@nx/webpack/plugin"
    ],
    "targets.preview.metadata": [
      "Ixeh/apps/Ixeh/webpack.config.js",
      "@nx/webpack/plugin"
    ],
    "targets.preview.executor": [
      "Ixeh/apps/Ixeh/webpack.config.js",
      "@nx/webpack/plugin"
    ],
    "targets.preview.options.cwd": [
      "Ixeh/apps/Ixeh/webpack.config.js",
      "@nx/webpack/plugin"
    ],
    "targets.preview.options.args": [
      "Ixeh/apps/Ixeh/webpack.config.js",
      "@nx/webpack/plugin"
    ],
    "targets.preview.options.command": [
      "Ixeh/apps/Ixeh/webpack.config.js",
      "@nx/webpack/plugin"
    ],
    "targets.preview.metadata.technologies": [
      "Ixeh/apps/Ixeh/webpack.config.js",
      "@nx/webpack/plugin"
    ],
    "targets.preview.metadata.technologies.0": [
      "Ixeh/apps/Ixeh/webpack.config.js",
      "@nx/webpack/plugin"
    ],
    "targets.preview.metadata.description": [
      "Ixeh/apps/Ixeh/webpack.config.js",
      "@nx/webpack/plugin"
    ],
    "targets.preview.metadata.help": [
      "Ixeh/apps/Ixeh/webpack.config.js",
      "@nx/webpack/plugin"
    ],
    "targets.preview.metadata.help.command": [
      "Ixeh/apps/Ixeh/webpack.config.js",
      "@nx/webpack/plugin"
    ],
    "targets.preview.metadata.help.example": [
      "Ixeh/apps/Ixeh/webpack.config.js",
      "@nx/webpack/plugin"
    ],
    "targets.serve-static": [
      "Ixeh/apps/Ixeh/webpack.config.js",
      "@nx/webpack/plugin"
    ],
    "targets.serve-static.continuous": [
      "Ixeh/apps/Ixeh/webpack.config.js",
      "@nx/webpack/plugin"
    ],
    "targets.serve-static.dependsOn": [
      "Ixeh/apps/Ixeh/webpack.config.js",
      "@nx/webpack/plugin"
    ],
    "targets.serve-static.executor": [
      "Ixeh/apps/Ixeh/webpack.config.js",
      "@nx/webpack/plugin"
    ],
    "targets.serve-static.options": [
      "Ixeh/apps/Ixeh/webpack.config.js",
      "@nx/webpack/plugin"
    ],
    "targets.serve-static.options.buildTarget": [
      "Ixeh/apps/Ixeh/webpack.config.js",
      "@nx/webpack/plugin"
    ],
    "targets.serve-static.options.spa": [
      "Ixeh/apps/Ixeh/webpack.config.js",
      "@nx/webpack/plugin"
    ],
    "targets.build-deps": [
      "Ixeh/apps/Ixeh/webpack.config.js",
      "@nx/webpack/plugin"
    ],
    "targets.build-deps.dependsOn": [
      "Ixeh/apps/Ixeh/webpack.config.js",
      "@nx/webpack/plugin"
    ],
    "targets.watch-deps": [
      "Ixeh/apps/Ixeh/webpack.config.js",
      "@nx/webpack/plugin"
    ],
    "targets.watch-deps.continuous": [
      "Ixeh/apps/Ixeh/webpack.config.js",
      "@nx/webpack/plugin"
    ],
    "targets.watch-deps.dependsOn": [
      "Ixeh/apps/Ixeh/webpack.config.js",
      "@nx/webpack/plugin"
    ],
    "targets.watch-deps.executor": [
      "Ixeh/apps/Ixeh/webpack.config.js",
      "@nx/webpack/plugin"
    ],
    "targets.watch-deps.options": [
      "Ixeh/apps/Ixeh/webpack.config.js",
      "@nx/webpack/plugin"
    ],
    "targets.watch-deps.options.command": [
      "Ixeh/apps/Ixeh/webpack.config.js",
      "@nx/webpack/plugin"
    ],
    "targets.eslint:lint": [
      "Ixeh/apps/Ixeh/eslint.config.mjs",
      "@nx/eslint/plugin"
    ],
    "targets.eslint:lint.cache": [
      "Ixeh/apps/Ixeh/eslint.config.mjs",
      "@nx/eslint/plugin"
    ],
    "targets.eslint:lint.options": [
      "Ixeh/apps/Ixeh/eslint.config.mjs",
      "@nx/eslint/plugin"
    ],
    "targets.eslint:lint.inputs": [
      "Ixeh/apps/Ixeh/eslint.config.mjs",
      "@nx/eslint/plugin"
    ],
    "targets.eslint:lint.outputs": [
      "Ixeh/apps/Ixeh/eslint.config.mjs",
      "@nx/eslint/plugin"
    ],
    "targets.eslint:lint.metadata": [
      "Ixeh/apps/Ixeh/eslint.config.mjs",
      "@nx/eslint/plugin"
    ],
    "targets.eslint:lint.executor": [
      "Ixeh/apps/Ixeh/eslint.config.mjs",
      "@nx/eslint/plugin"
    ],
    "targets.eslint:lint.options.cwd": [
      "Ixeh/apps/Ixeh/eslint.config.mjs",
      "@nx/eslint/plugin"
    ],
    "targets.eslint:lint.options.command": [
      "Ixeh/apps/Ixeh/eslint.config.mjs",
      "@nx/eslint/plugin"
    ],
    "targets.eslint:lint.metadata.technologies": [
      "Ixeh/apps/Ixeh/eslint.config.mjs",
      "@nx/eslint/plugin"
    ],
    "targets.eslint:lint.metadata.technologies.0": [
      "Ixeh/apps/Ixeh/eslint.config.mjs",
      "@nx/eslint/plugin"
    ],
    "targets.eslint:lint.metadata.description": [
      "Ixeh/apps/Ixeh/eslint.config.mjs",
      "@nx/eslint/plugin"
    ],
    "targets.eslint:lint.metadata.help": [
      "Ixeh/apps/Ixeh/eslint.config.mjs",
      "@nx/eslint/plugin"
    ],
    "targets.eslint:lint.metadata.help.command": [
      "Ixeh/apps/Ixeh/eslint.config.mjs",
      "@nx/eslint/plugin"
    ],
    "targets.eslint:lint.metadata.help.example": [
      "Ixeh/apps/Ixeh/eslint.config.mjs",
      "@nx/eslint/plugin"
    ]
  },
  "apps/gateway-api": {
    "root": [
      "apps/gateway-api/project.json",
      "nx/core/project-json"
    ],
    "projectType": [
      "apps/gateway-api/project.json",
      "nx/core/project-json"
    ],
    "targets": [
      "apps/gateway-api/webpack.config.js",
      "@nx/webpack/plugin"
    ],
    "targets.build": [
      "apps/gateway-api/project.json",
      "nx/core/project-json"
    ],
    "targets.build.options": [
      "apps/gateway-api/project.json",
      "nx/core/project-json"
    ],
    "targets.build.cache": [
      "apps/gateway-api/webpack.config.js",
      "@nx/webpack/plugin"
    ],
    "targets.build.dependsOn": [
      "apps/gateway-api/webpack.config.js",
      "@nx/webpack/plugin"
    ],
    "targets.build.inputs": [
      "apps/gateway-api/webpack.config.js",
      "@nx/webpack/plugin"
    ],
    "targets.build.outputs": [
      "apps/gateway-api/webpack.config.js",
      "@nx/webpack/plugin"
    ],
    "targets.build.metadata": [
      "apps/gateway-api/webpack.config.js",
      "@nx/webpack/plugin"
    ],
    "targets.build.executor": [
      "apps/gateway-api/project.json",
      "nx/core/project-json"
    ],
    "targets.build.options.cwd": [
      "apps/gateway-api/project.json",
      "nx/core/project-json"
    ],
    "targets.build.options.args": [
      "apps/gateway-api/project.json",
      "nx/core/project-json"
    ],
    "targets.build.options.command": [
      "apps/gateway-api/project.json",
      "nx/core/project-json"
    ],
    "targets.build.metadata.technologies": [
      "apps/gateway-api/webpack.config.js",
      "@nx/webpack/plugin"
    ],
    "targets.build.metadata.technologies.0": [
      "apps/gateway-api/webpack.config.js",
      "@nx/webpack/plugin"
    ],
    "targets.build.metadata.description": [
      "apps/gateway-api/webpack.config.js",
      "@nx/webpack/plugin"
    ],
    "targets.build.metadata.help": [
      "apps/gateway-api/webpack.config.js",
      "@nx/webpack/plugin"
    ],
    "targets.build.metadata.help.command": [
      "apps/gateway-api/webpack.config.js",
      "@nx/webpack/plugin"
    ],
    "targets.build.metadata.help.example": [
      "apps/gateway-api/webpack.config.js",
      "@nx/webpack/plugin"
    ],
    "targets.preview": [
      "apps/gateway-api/webpack.config.js",
      "@nx/webpack/plugin"
    ],
    "targets.preview.continuous": [
      "apps/gateway-api/webpack.config.js",
      "@nx/webpack/plugin"
    ],
    "targets.preview.options": [
      "apps/gateway-api/webpack.config.js",
      "@nx/webpack/plugin"
    ],
    "targets.preview.metadata": [
      "apps/gateway-api/webpack.config.js",
      "@nx/webpack/plugin"
    ],
    "targets.preview.executor": [
      "apps/gateway-api/webpack.config.js",
      "@nx/webpack/plugin"
    ],
    "targets.preview.options.cwd": [
      "apps/gateway-api/webpack.config.js",
      "@nx/webpack/plugin"
    ],
    "targets.preview.options.args": [
      "apps/gateway-api/webpack.config.js",
      "@nx/webpack/plugin"
    ],
    "targets.preview.options.command": [
      "apps/gateway-api/webpack.config.js",
      "@nx/webpack/plugin"
    ],
    "targets.preview.metadata.technologies": [
      "apps/gateway-api/webpack.config.js",
      "@nx/webpack/plugin"
    ],
    "targets.preview.metadata.technologies.0": [
      "apps/gateway-api/webpack.config.js",
      "@nx/webpack/plugin"
    ],
    "targets.preview.metadata.description": [
      "apps/gateway-api/webpack.config.js",
      "@nx/webpack/plugin"
    ],
    "targets.preview.metadata.help": [
      "apps/gateway-api/webpack.config.js",
      "@nx/webpack/plugin"
    ],
    "targets.preview.metadata.help.command": [
      "apps/gateway-api/webpack.config.js",
      "@nx/webpack/plugin"
    ],
    "targets.preview.metadata.help.example": [
      "apps/gateway-api/webpack.config.js",
      "@nx/webpack/plugin"
    ],
    "targets.build-deps": [
      "apps/gateway-api/webpack.config.js",
      "@nx/webpack/plugin"
    ],
    "targets.build-deps.dependsOn": [
      "apps/gateway-api/webpack.config.js",
      "@nx/webpack/plugin"
    ],
    "targets.watch-deps": [
      "apps/gateway-api/webpack.config.js",
      "@nx/webpack/plugin"
    ],
    "targets.watch-deps.continuous": [
      "apps/gateway-api/webpack.config.js",
      "@nx/webpack/plugin"
    ],
    "targets.watch-deps.dependsOn": [
      "apps/gateway-api/webpack.config.js",
      "@nx/webpack/plugin"
    ],
    "targets.watch-deps.executor": [
      "apps/gateway-api/webpack.config.js",
      "@nx/webpack/plugin"
    ],
    "targets.watch-deps.options": [
      "apps/gateway-api/webpack.config.js",
      "@nx/webpack/plugin"
    ],
    "targets.watch-deps.options.command": [
      "apps/gateway-api/webpack.config.js",
      "@nx/webpack/plugin"
    ],
    "targets.test": [
      "apps/gateway-api/project.json",
      "nx/core/project-json"
    ],
    "targets.test.options": [
      "apps/gateway-api/project.json",
      "nx/core/project-json"
    ],
    "targets.test.metadata": [
      "apps/gateway-api/jest.config.ts",
      "@nx/jest/plugin"
    ],
    "targets.test.cache": [
      "apps/gateway-api/jest.config.ts",
      "@nx/jest/plugin"
    ],
    "targets.test.inputs": [
      "apps/gateway-api/jest.config.ts",
      "@nx/jest/plugin"
    ],
    "targets.test.outputs": [
      "apps/gateway-api/jest.config.ts",
      "@nx/jest/plugin"
    ],
    "targets.test.executor": [
      "apps/gateway-api/jest.config.ts",
      "@nx/jest/plugin"
    ],
    "targets.test.options.cwd": [
      "apps/gateway-api/jest.config.ts",
      "@nx/jest/plugin"
    ],
    "targets.test.options.env": [
      "apps/gateway-api/jest.config.ts",
      "@nx/jest/plugin"
    ],
    "targets.test.options.command": [
      "apps/gateway-api/jest.config.ts",
      "@nx/jest/plugin"
    ],
    "targets.test.metadata.technologies": [
      "apps/gateway-api/jest.config.ts",
      "@nx/jest/plugin"
    ],
    "targets.test.metadata.technologies.0": [
      "apps/gateway-api/jest.config.ts",
      "@nx/jest/plugin"
    ],
    "targets.test.metadata.description": [
      "apps/gateway-api/jest.config.ts",
      "@nx/jest/plugin"
    ],
    "targets.test.metadata.help": [
      "apps/gateway-api/jest.config.ts",
      "@nx/jest/plugin"
    ],
    "targets.test.metadata.help.command": [
      "apps/gateway-api/jest.config.ts",
      "@nx/jest/plugin"
    ],
    "targets.test.metadata.help.example": [
      "apps/gateway-api/jest.config.ts",
      "@nx/jest/plugin"
    ],
    "targets.eslint:lint": [
      "apps/gateway-api/eslint.config.mjs",
      "@nx/eslint/plugin"
    ],
    "targets.eslint:lint.cache": [
      "apps/gateway-api/eslint.config.mjs",
      "@nx/eslint/plugin"
    ],
    "targets.eslint:lint.options": [
      "apps/gateway-api/eslint.config.mjs",
      "@nx/eslint/plugin"
    ],
    "targets.eslint:lint.inputs": [
      "apps/gateway-api/eslint.config.mjs",
      "@nx/eslint/plugin"
    ],
    "targets.eslint:lint.outputs": [
      "apps/gateway-api/eslint.config.mjs",
      "@nx/eslint/plugin"
    ],
    "targets.eslint:lint.metadata": [
      "apps/gateway-api/eslint.config.mjs",
      "@nx/eslint/plugin"
    ],
    "targets.eslint:lint.executor": [
      "apps/gateway-api/eslint.config.mjs",
      "@nx/eslint/plugin"
    ],
    "targets.eslint:lint.options.cwd": [
      "apps/gateway-api/eslint.config.mjs",
      "@nx/eslint/plugin"
    ],
    "targets.eslint:lint.options.command": [
      "apps/gateway-api/eslint.config.mjs",
      "@nx/eslint/plugin"
    ],
    "targets.eslint:lint.metadata.technologies": [
      "apps/gateway-api/eslint.config.mjs",
      "@nx/eslint/plugin"
    ],
    "targets.eslint:lint.metadata.technologies.0": [
      "apps/gateway-api/eslint.config.mjs",
      "@nx/eslint/plugin"
    ],
    "targets.eslint:lint.metadata.description": [
      "apps/gateway-api/eslint.config.mjs",
      "@nx/eslint/plugin"
    ],
    "targets.eslint:lint.metadata.help": [
      "apps/gateway-api/eslint.config.mjs",
      "@nx/eslint/plugin"
    ],
    "targets.eslint:lint.metadata.help.command": [
      "apps/gateway-api/eslint.config.mjs",
      "@nx/eslint/plugin"
    ],
    "targets.eslint:lint.metadata.help.example": [
      "apps/gateway-api/eslint.config.mjs",
      "@nx/eslint/plugin"
    ],
    "name": [
      "apps/gateway-api/project.json",
      "nx/core/project-json"
    ],
    "$schema": [
      "apps/gateway-api/project.json",
      "nx/core/project-json"
    ],
    "sourceRoot": [
      "apps/gateway-api/project.json",
      "nx/core/project-json"
    ],
    "tags": [
      "apps/gateway-api/project.json",
      "nx/core/project-json"
    ],
    "targets.build.configurations": [
      "apps/gateway-api/project.json",
      "nx/core/project-json"
    ],
    "targets.build.configurations.development": [
      "apps/gateway-api/project.json",
      "nx/core/project-json"
    ],
    "targets.build.configurations.development.args": [
      "apps/gateway-api/project.json",
      "nx/core/project-json"
    ],
    "targets.prune-lockfile": [
      "apps/gateway-api/project.json",
      "nx/core/project-json"
    ],
    "targets.prune-lockfile.dependsOn": [
      "apps/gateway-api/project.json",
      "nx/core/project-json"
    ],
    "targets.prune-lockfile.cache": [
      "apps/gateway-api/project.json",
      "nx/core/project-json"
    ],
    "targets.prune-lockfile.executor": [
      "apps/gateway-api/project.json",
      "nx/core/project-json"
    ],
    "targets.prune-lockfile.outputs": [
      "apps/gateway-api/project.json",
      "nx/core/project-json"
    ],
    "targets.prune-lockfile.options": [
      "apps/gateway-api/project.json",
      "nx/core/project-json"
    ],
    "targets.prune-lockfile.options.buildTarget": [
      "apps/gateway-api/project.json",
      "nx/core/project-json"
    ],
    "targets.copy-workspace-modules": [
      "apps/gateway-api/project.json",
      "nx/core/project-json"
    ],
    "targets.copy-workspace-modules.dependsOn": [
      "apps/gateway-api/project.json",
      "nx/core/project-json"
    ],
    "targets.copy-workspace-modules.cache": [
      "apps/gateway-api/project.json",
      "nx/core/project-json"
    ],
    "targets.copy-workspace-modules.outputs": [
      "apps/gateway-api/project.json",
      "nx/core/project-json"
    ],
    "targets.copy-workspace-modules.executor": [
      "apps/gateway-api/project.json",
      "nx/core/project-json"
    ],
    "targets.copy-workspace-modules.options": [
      "apps/gateway-api/project.json",
      "nx/core/project-json"
    ],
    "targets.copy-workspace-modules.options.buildTarget": [
      "apps/gateway-api/project.json",
      "nx/core/project-json"
    ],
    "targets.prune": [
      "apps/gateway-api/project.json",
      "nx/core/project-json"
    ],
    "targets.prune.dependsOn": [
      "apps/gateway-api/project.json",
      "nx/core/project-json"
    ],
    "targets.prune.executor": [
      "apps/gateway-api/project.json",
      "nx/core/project-json"
    ],
    "targets.serve": [
      "apps/gateway-api/project.json",
      "nx/core/project-json"
    ],
    "targets.serve.continuous": [
      "apps/gateway-api/project.json",
      "nx/core/project-json"
    ],
    "targets.serve.executor": [
      "apps/gateway-api/project.json",
      "nx/core/project-json"
    ],
    "targets.serve.defaultConfiguration": [
      "apps/gateway-api/project.json",
      "nx/core/project-json"
    ],
    "targets.serve.dependsOn": [
      "apps/gateway-api/project.json",
      "nx/core/project-json"
    ],
    "targets.serve.options": [
      "apps/gateway-api/project.json",
      "nx/core/project-json"
    ],
    "targets.serve.configurations": [
      "apps/gateway-api/project.json",
      "nx/core/project-json"
    ],
    "targets.serve.options.buildTarget": [
      "apps/gateway-api/project.json",
      "nx/core/project-json"
    ],
    "targets.serve.options.runBuildTargetDependencies": [
      "apps/gateway-api/project.json",
      "nx/core/project-json"
    ],
    "targets.serve.configurations.development": [
      "apps/gateway-api/project.json",
      "nx/core/project-json"
    ],
    "targets.serve.configurations.development.buildTarget": [
      "apps/gateway-api/project.json",
      "nx/core/project-json"
    ],
    "targets.serve.configurations.production": [
      "apps/gateway-api/project.json",
      "nx/core/project-json"
    ],
    "targets.serve.configurations.production.buildTarget": [
      "apps/gateway-api/project.json",
      "nx/core/project-json"
    ],
    "targets.test.options.passWithNoTests": [
      "apps/gateway-api/project.json",
      "nx/core/project-json"
    ]
  },
  "apps/whatsapp-microservice": {
    "root": [
      "apps/whatsapp-microservice/project.json",
      "nx/core/project-json"
    ],
    "projectType": [
      "apps/whatsapp-microservice/project.json",
      "nx/core/project-json"
    ],
    "targets": [
      "apps/whatsapp-microservice/webpack.config.js",
      "@nx/webpack/plugin"
    ],
    "targets.build": [
      "apps/whatsapp-microservice/project.json",
      "nx/core/project-json"
    ],
    "targets.build.options": [
      "apps/whatsapp-microservice/project.json",
      "nx/core/project-json"
    ],
    "targets.build.cache": [
      "apps/whatsapp-microservice/webpack.config.js",
      "@nx/webpack/plugin"
    ],
    "targets.build.dependsOn": [
      "apps/whatsapp-microservice/webpack.config.js",
      "@nx/webpack/plugin"
    ],
    "targets.build.inputs": [
      "apps/whatsapp-microservice/webpack.config.js",
      "@nx/webpack/plugin"
    ],
    "targets.build.outputs": [
      "apps/whatsapp-microservice/webpack.config.js",
      "@nx/webpack/plugin"
    ],
    "targets.build.metadata": [
      "apps/whatsapp-microservice/webpack.config.js",
      "@nx/webpack/plugin"
    ],
    "targets.build.executor": [
      "apps/whatsapp-microservice/project.json",
      "nx/core/project-json"
    ],
    "targets.build.options.cwd": [
      "apps/whatsapp-microservice/project.json",
      "nx/core/project-json"
    ],
    "targets.build.options.args": [
      "apps/whatsapp-microservice/project.json",
      "nx/core/project-json"
    ],
    "targets.build.options.command": [
      "apps/whatsapp-microservice/project.json",
      "nx/core/project-json"
    ],
    "targets.build.metadata.technologies": [
      "apps/whatsapp-microservice/webpack.config.js",
      "@nx/webpack/plugin"
    ],
    "targets.build.metadata.technologies.0": [
      "apps/whatsapp-microservice/webpack.config.js",
      "@nx/webpack/plugin"
    ],
    "targets.build.metadata.description": [
      "apps/whatsapp-microservice/webpack.config.js",
      "@nx/webpack/plugin"
    ],
    "targets.build.metadata.help": [
      "apps/whatsapp-microservice/webpack.config.js",
      "@nx/webpack/plugin"
    ],
    "targets.build.metadata.help.command": [
      "apps/whatsapp-microservice/webpack.config.js",
      "@nx/webpack/plugin"
    ],
    "targets.build.metadata.help.example": [
      "apps/whatsapp-microservice/webpack.config.js",
      "@nx/webpack/plugin"
    ],
    "targets.preview": [
      "apps/whatsapp-microservice/webpack.config.js",
      "@nx/webpack/plugin"
    ],
    "targets.preview.continuous": [
      "apps/whatsapp-microservice/webpack.config.js",
      "@nx/webpack/plugin"
    ],
    "targets.preview.options": [
      "apps/whatsapp-microservice/webpack.config.js",
      "@nx/webpack/plugin"
    ],
    "targets.preview.metadata": [
      "apps/whatsapp-microservice/webpack.config.js",
      "@nx/webpack/plugin"
    ],
    "targets.preview.executor": [
      "apps/whatsapp-microservice/webpack.config.js",
      "@nx/webpack/plugin"
    ],
    "targets.preview.options.cwd": [
      "apps/whatsapp-microservice/webpack.config.js",
      "@nx/webpack/plugin"
    ],
    "targets.preview.options.args": [
      "apps/whatsapp-microservice/webpack.config.js",
      "@nx/webpack/plugin"
    ],
    "targets.preview.options.command": [
      "apps/whatsapp-microservice/webpack.config.js",
      "@nx/webpack/plugin"
    ],
    "targets.preview.metadata.technologies": [
      "apps/whatsapp-microservice/webpack.config.js",
      "@nx/webpack/plugin"
    ],
    "targets.preview.metadata.technologies.0": [
      "apps/whatsapp-microservice/webpack.config.js",
      "@nx/webpack/plugin"
    ],
    "targets.preview.metadata.description": [
      "apps/whatsapp-microservice/webpack.config.js",
      "@nx/webpack/plugin"
    ],
    "targets.preview.metadata.help": [
      "apps/whatsapp-microservice/webpack.config.js",
      "@nx/webpack/plugin"
    ],
    "targets.preview.metadata.help.command": [
      "apps/whatsapp-microservice/webpack.config.js",
      "@nx/webpack/plugin"
    ],
    "targets.preview.metadata.help.example": [
      "apps/whatsapp-microservice/webpack.config.js",
      "@nx/webpack/plugin"
    ],
    "targets.build-deps": [
      "apps/whatsapp-microservice/webpack.config.js",
      "@nx/webpack/plugin"
    ],
    "targets.build-deps.dependsOn": [
      "apps/whatsapp-microservice/webpack.config.js",
      "@nx/webpack/plugin"
    ],
    "targets.watch-deps": [
      "apps/whatsapp-microservice/webpack.config.js",
      "@nx/webpack/plugin"
    ],
    "targets.watch-deps.continuous": [
      "apps/whatsapp-microservice/webpack.config.js",
      "@nx/webpack/plugin"
    ],
    "targets.watch-deps.dependsOn": [
      "apps/whatsapp-microservice/webpack.config.js",
      "@nx/webpack/plugin"
    ],
    "targets.watch-deps.executor": [
      "apps/whatsapp-microservice/webpack.config.js",
      "@nx/webpack/plugin"
    ],
    "targets.watch-deps.options": [
      "apps/whatsapp-microservice/webpack.config.js",
      "@nx/webpack/plugin"
    ],
    "targets.watch-deps.options.command": [
      "apps/whatsapp-microservice/webpack.config.js",
      "@nx/webpack/plugin"
    ],
    "targets.test": [
      "apps/whatsapp-microservice/project.json",
      "nx/core/project-json"
    ],
    "targets.test.options": [
      "apps/whatsapp-microservice/project.json",
      "nx/core/project-json"
    ],
    "targets.test.metadata": [
      "apps/whatsapp-microservice/jest.config.ts",
      "@nx/jest/plugin"
    ],
    "targets.test.cache": [
      "apps/whatsapp-microservice/jest.config.ts",
      "@nx/jest/plugin"
    ],
    "targets.test.inputs": [
      "apps/whatsapp-microservice/jest.config.ts",
      "@nx/jest/plugin"
    ],
    "targets.test.outputs": [
      "apps/whatsapp-microservice/jest.config.ts",
      "@nx/jest/plugin"
    ],
    "targets.test.executor": [
      "apps/whatsapp-microservice/jest.config.ts",
      "@nx/jest/plugin"
    ],
    "targets.test.options.cwd": [
      "apps/whatsapp-microservice/jest.config.ts",
      "@nx/jest/plugin"
    ],
    "targets.test.options.env": [
      "apps/whatsapp-microservice/jest.config.ts",
      "@nx/jest/plugin"
    ],
    "targets.test.options.command": [
      "apps/whatsapp-microservice/jest.config.ts",
      "@nx/jest/plugin"
    ],
    "targets.test.metadata.technologies": [
      "apps/whatsapp-microservice/jest.config.ts",
      "@nx/jest/plugin"
    ],
    "targets.test.metadata.technologies.0": [
      "apps/whatsapp-microservice/jest.config.ts",
      "@nx/jest/plugin"
    ],
    "targets.test.metadata.description": [
      "apps/whatsapp-microservice/jest.config.ts",
      "@nx/jest/plugin"
    ],
    "targets.test.metadata.help": [
      "apps/whatsapp-microservice/jest.config.ts",
      "@nx/jest/plugin"
    ],
    "targets.test.metadata.help.command": [
      "apps/whatsapp-microservice/jest.config.ts",
      "@nx/jest/plugin"
    ],
    "targets.test.metadata.help.example": [
      "apps/whatsapp-microservice/jest.config.ts",
      "@nx/jest/plugin"
    ],
    "targets.eslint:lint": [
      "eslint.config.mjs",
      "@nx/eslint/plugin"
    ],
    "targets.eslint:lint.cache": [
      "eslint.config.mjs",
      "@nx/eslint/plugin"
    ],
    "targets.eslint:lint.options": [
      "eslint.config.mjs",
      "@nx/eslint/plugin"
    ],
    "targets.eslint:lint.inputs": [
      "eslint.config.mjs",
      "@nx/eslint/plugin"
    ],
    "targets.eslint:lint.outputs": [
      "eslint.config.mjs",
      "@nx/eslint/plugin"
    ],
    "targets.eslint:lint.metadata": [
      "eslint.config.mjs",
      "@nx/eslint/plugin"
    ],
    "targets.eslint:lint.executor": [
      "eslint.config.mjs",
      "@nx/eslint/plugin"
    ],
    "targets.eslint:lint.options.cwd": [
      "eslint.config.mjs",
      "@nx/eslint/plugin"
    ],
    "targets.eslint:lint.options.command": [
      "eslint.config.mjs",
      "@nx/eslint/plugin"
    ],
    "targets.eslint:lint.metadata.technologies": [
      "eslint.config.mjs",
      "@nx/eslint/plugin"
    ],
    "targets.eslint:lint.metadata.technologies.0": [
      "eslint.config.mjs",
      "@nx/eslint/plugin"
    ],
    "targets.eslint:lint.metadata.description": [
      "eslint.config.mjs",
      "@nx/eslint/plugin"
    ],
    "targets.eslint:lint.metadata.help": [
      "eslint.config.mjs",
      "@nx/eslint/plugin"
    ],
    "targets.eslint:lint.metadata.help.command": [
      "eslint.config.mjs",
      "@nx/eslint/plugin"
    ],
    "targets.eslint:lint.metadata.help.example": [
      "eslint.config.mjs",
      "@nx/eslint/plugin"
    ],
    "name": [
      "apps/whatsapp-microservice/project.json",
      "nx/core/project-json"
    ],
    "$schema": [
      "apps/whatsapp-microservice/project.json",
      "nx/core/project-json"
    ],
    "sourceRoot": [
      "apps/whatsapp-microservice/project.json",
      "nx/core/project-json"
    ],
    "tags": [
      "apps/whatsapp-microservice/project.json",
      "nx/core/project-json"
    ],
    "targets.build.configurations": [
      "apps/whatsapp-microservice/project.json",
      "nx/core/project-json"
    ],
    "targets.build.configurations.development": [
      "apps/whatsapp-microservice/project.json",
      "nx/core/project-json"
    ],
    "targets.build.configurations.development.args": [
      "apps/whatsapp-microservice/project.json",
      "nx/core/project-json"
    ],
    "targets.prune-lockfile": [
      "apps/whatsapp-microservice/project.json",
      "nx/core/project-json"
    ],
    "targets.prune-lockfile.dependsOn": [
      "apps/whatsapp-microservice/project.json",
      "nx/core/project-json"
    ],
    "targets.prune-lockfile.cache": [
      "apps/whatsapp-microservice/project.json",
      "nx/core/project-json"
    ],
    "targets.prune-lockfile.executor": [
      "apps/whatsapp-microservice/project.json",
      "nx/core/project-json"
    ],
    "targets.prune-lockfile.outputs": [
      "apps/whatsapp-microservice/project.json",
      "nx/core/project-json"
    ],
    "targets.prune-lockfile.options": [
      "apps/whatsapp-microservice/project.json",
      "nx/core/project-json"
    ],
    "targets.prune-lockfile.options.buildTarget": [
      "apps/whatsapp-microservice/project.json",
      "nx/core/project-json"
    ],
    "targets.copy-workspace-modules": [
      "apps/whatsapp-microservice/project.json",
      "nx/core/project-json"
    ],
    "targets.copy-workspace-modules.dependsOn": [
      "apps/whatsapp-microservice/project.json",
      "nx/core/project-json"
    ],
    "targets.copy-workspace-modules.cache": [
      "apps/whatsapp-microservice/project.json",
      "nx/core/project-json"
    ],
    "targets.copy-workspace-modules.outputs": [
      "apps/whatsapp-microservice/project.json",
      "nx/core/project-json"
    ],
    "targets.copy-workspace-modules.executor": [
      "apps/whatsapp-microservice/project.json",
      "nx/core/project-json"
    ],
    "targets.copy-workspace-modules.options": [
      "apps/whatsapp-microservice/project.json",
      "nx/core/project-json"
    ],
    "targets.copy-workspace-modules.options.buildTarget": [
      "apps/whatsapp-microservice/project.json",
      "nx/core/project-json"
    ],
    "targets.prune": [
      "apps/whatsapp-microservice/project.json",
      "nx/core/project-json"
    ],
    "targets.prune.dependsOn": [
      "apps/whatsapp-microservice/project.json",
      "nx/core/project-json"
    ],
    "targets.prune.executor": [
      "apps/whatsapp-microservice/project.json",
      "nx/core/project-json"
    ],
    "targets.serve": [
      "apps/whatsapp-microservice/project.json",
      "nx/core/project-json"
    ],
    "targets.serve.continuous": [
      "apps/whatsapp-microservice/project.json",
      "nx/core/project-json"
    ],
    "targets.serve.executor": [
      "apps/whatsapp-microservice/project.json",
      "nx/core/project-json"
    ],
    "targets.serve.defaultConfiguration": [
      "apps/whatsapp-microservice/project.json",
      "nx/core/project-json"
    ],
    "targets.serve.dependsOn": [
      "apps/whatsapp-microservice/project.json",
      "nx/core/project-json"
    ],
    "targets.serve.options": [
      "apps/whatsapp-microservice/project.json",
      "nx/core/project-json"
    ],
    "targets.serve.configurations": [
      "apps/whatsapp-microservice/project.json",
      "nx/core/project-json"
    ],
    "targets.serve.options.buildTarget": [
      "apps/whatsapp-microservice/project.json",
      "nx/core/project-json"
    ],
    "targets.serve.options.runBuildTargetDependencies": [
      "apps/whatsapp-microservice/project.json",
      "nx/core/project-json"
    ],
    "targets.serve.configurations.development": [
      "apps/whatsapp-microservice/project.json",
      "nx/core/project-json"
    ],
    "targets.serve.configurations.development.buildTarget": [
      "apps/whatsapp-microservice/project.json",
      "nx/core/project-json"
    ],
    "targets.serve.configurations.production": [
      "apps/whatsapp-microservice/project.json",
      "nx/core/project-json"
    ],
    "targets.serve.configurations.production.buildTarget": [
      "apps/whatsapp-microservice/project.json",
      "nx/core/project-json"
    ],
    "targets.test.options.passWithNoTests": [
      "apps/whatsapp-microservice/project.json",
      "nx/core/project-json"
    ]
  },
  "Ixeh/apps/Ixeh-e2e": {
    "root": [
      "Ixeh/apps/Ixeh-e2e/eslint.config.mjs",
      "@nx/eslint/plugin"
    ],
    "targets": [
      "Ixeh/apps/Ixeh-e2e/eslint.config.mjs",
      "@nx/eslint/plugin"
    ],
    "targets.eslint:lint": [
      "Ixeh/apps/Ixeh-e2e/eslint.config.mjs",
      "@nx/eslint/plugin"
    ],
    "targets.eslint:lint.cache": [
      "Ixeh/apps/Ixeh-e2e/eslint.config.mjs",
      "@nx/eslint/plugin"
    ],
    "targets.eslint:lint.options": [
      "Ixeh/apps/Ixeh-e2e/eslint.config.mjs",
      "@nx/eslint/plugin"
    ],
    "targets.eslint:lint.inputs": [
      "Ixeh/apps/Ixeh-e2e/eslint.config.mjs",
      "@nx/eslint/plugin"
    ],
    "targets.eslint:lint.outputs": [
      "Ixeh/apps/Ixeh-e2e/eslint.config.mjs",
      "@nx/eslint/plugin"
    ],
    "targets.eslint:lint.metadata": [
      "Ixeh/apps/Ixeh-e2e/eslint.config.mjs",
      "@nx/eslint/plugin"
    ],
    "targets.eslint:lint.executor": [
      "Ixeh/apps/Ixeh-e2e/eslint.config.mjs",
      "@nx/eslint/plugin"
    ],
    "targets.eslint:lint.options.cwd": [
      "Ixeh/apps/Ixeh-e2e/eslint.config.mjs",
      "@nx/eslint/plugin"
    ],
    "targets.eslint:lint.options.command": [
      "Ixeh/apps/Ixeh-e2e/eslint.config.mjs",
      "@nx/eslint/plugin"
    ],
    "targets.eslint:lint.metadata.technologies": [
      "Ixeh/apps/Ixeh-e2e/eslint.config.mjs",
      "@nx/eslint/plugin"
    ],
    "targets.eslint:lint.metadata.technologies.0": [
      "Ixeh/apps/Ixeh-e2e/eslint.config.mjs",
      "@nx/eslint/plugin"
    ],
    "targets.eslint:lint.metadata.description": [
      "Ixeh/apps/Ixeh-e2e/eslint.config.mjs",
      "@nx/eslint/plugin"
    ],
    "targets.eslint:lint.metadata.help": [
      "Ixeh/apps/Ixeh-e2e/eslint.config.mjs",
      "@nx/eslint/plugin"
    ],
    "targets.eslint:lint.metadata.help.command": [
      "Ixeh/apps/Ixeh-e2e/eslint.config.mjs",
      "@nx/eslint/plugin"
    ],
    "targets.eslint:lint.metadata.help.example": [
      "Ixeh/apps/Ixeh-e2e/eslint.config.mjs",
      "@nx/eslint/plugin"
    ]
  },
  "Ixeh": {
    "root": [
      "Ixeh/eslint.config.mjs",
      "@nx/eslint/plugin"
    ],
    "targets": [
      "Ixeh/eslint.config.mjs",
      "@nx/eslint/plugin"
    ],
    "targets.eslint:lint": [
      "Ixeh/eslint.config.mjs",
      "@nx/eslint/plugin"
    ],
    "targets.eslint:lint.cache": [
      "Ixeh/eslint.config.mjs",
      "@nx/eslint/plugin"
    ],
    "targets.eslint:lint.options": [
      "Ixeh/eslint.config.mjs",
      "@nx/eslint/plugin"
    ],
    "targets.eslint:lint.inputs": [
      "Ixeh/eslint.config.mjs",
      "@nx/eslint/plugin"
    ],
    "targets.eslint:lint.outputs": [
      "Ixeh/eslint.config.mjs",
      "@nx/eslint/plugin"
    ],
    "targets.eslint:lint.metadata": [
      "Ixeh/eslint.config.mjs",
      "@nx/eslint/plugin"
    ],
    "targets.eslint:lint.executor": [
      "Ixeh/eslint.config.mjs",
      "@nx/eslint/plugin"
    ],
    "targets.eslint:lint.options.cwd": [
      "Ixeh/eslint.config.mjs",
      "@nx/eslint/plugin"
    ],
    "targets.eslint:lint.options.command": [
      "Ixeh/eslint.config.mjs",
      "@nx/eslint/plugin"
    ],
    "targets.eslint:lint.metadata.technologies": [
      "Ixeh/eslint.config.mjs",
      "@nx/eslint/plugin"
    ],
    "targets.eslint:lint.metadata.technologies.0": [
      "Ixeh/eslint.config.mjs",
      "@nx/eslint/plugin"
    ],
    "targets.eslint:lint.metadata.description": [
      "Ixeh/eslint.config.mjs",
      "@nx/eslint/plugin"
    ],
    "targets.eslint:lint.metadata.help": [
      "Ixeh/eslint.config.mjs",
      "@nx/eslint/plugin"
    ],
    "targets.eslint:lint.metadata.help.command": [
      "Ixeh/eslint.config.mjs",
      "@nx/eslint/plugin"
    ],
    "targets.eslint:lint.metadata.help.example": [
      "Ixeh/eslint.config.mjs",
      "@nx/eslint/plugin"
    ]
  },
  "apps/gateway": {
    "root": [
      "apps/gateway/package.json",
      "nx/core/package-json"
    ],
    "targets": [
      "apps/gateway/eslint.config.mjs",
      "@nx/eslint/plugin"
    ],
    "targets.eslint:lint": [
      "apps/gateway/eslint.config.mjs",
      "@nx/eslint/plugin"
    ],
    "targets.eslint:lint.cache": [
      "apps/gateway/eslint.config.mjs",
      "@nx/eslint/plugin"
    ],
    "targets.eslint:lint.options": [
      "apps/gateway/eslint.config.mjs",
      "@nx/eslint/plugin"
    ],
    "targets.eslint:lint.inputs": [
      "apps/gateway/eslint.config.mjs",
      "@nx/eslint/plugin"
    ],
    "targets.eslint:lint.outputs": [
      "apps/gateway/eslint.config.mjs",
      "@nx/eslint/plugin"
    ],
    "targets.eslint:lint.metadata": [
      "apps/gateway/eslint.config.mjs",
      "@nx/eslint/plugin"
    ],
    "targets.eslint:lint.executor": [
      "apps/gateway/eslint.config.mjs",
      "@nx/eslint/plugin"
    ],
    "targets.eslint:lint.options.cwd": [
      "apps/gateway/eslint.config.mjs",
      "@nx/eslint/plugin"
    ],
    "targets.eslint:lint.options.command": [
      "apps/gateway/eslint.config.mjs",
      "@nx/eslint/plugin"
    ],
    "targets.eslint:lint.metadata.technologies": [
      "apps/gateway/eslint.config.mjs",
      "@nx/eslint/plugin"
    ],
    "targets.eslint:lint.metadata.technologies.0": [
      "apps/gateway/eslint.config.mjs",
      "@nx/eslint/plugin"
    ],
    "targets.eslint:lint.metadata.description": [
      "apps/gateway/eslint.config.mjs",
      "@nx/eslint/plugin"
    ],
    "targets.eslint:lint.metadata.help": [
      "apps/gateway/eslint.config.mjs",
      "@nx/eslint/plugin"
    ],
    "targets.eslint:lint.metadata.help.command": [
      "apps/gateway/eslint.config.mjs",
      "@nx/eslint/plugin"
    ],
    "targets.eslint:lint.metadata.help.example": [
      "apps/gateway/eslint.config.mjs",
      "@nx/eslint/plugin"
    ],
    "name": [
      "apps/gateway/package.json",
      "nx/core/package-json"
    ],
    "tags": [
      "apps/gateway/package.json",
      "nx/core/package-json"
    ],
    "tags.npm:private": [
      "apps/gateway/package.json",
      "nx/core/package-json"
    ],
    "metadata.targetGroups": [
      "apps/gateway/package.json",
      "nx/core/package-json"
    ],
    "metadata.targetGroups.NPM Scripts": [
      "apps/gateway/package.json",
      "nx/core/package-json"
    ],
    "metadata.targetGroups.NPM Scripts.0": [
      "apps/gateway/package.json",
      "nx/core/package-json"
    ],
    "metadata.targetGroups.NPM Scripts.1": [
      "apps/gateway/package.json",
      "nx/core/package-json"
    ],
    "metadata.targetGroups.NPM Scripts.2": [
      "apps/gateway/package.json",
      "nx/core/package-json"
    ],
    "metadata.targetGroups.NPM Scripts.3": [
      "apps/gateway/package.json",
      "nx/core/package-json"
    ],
    "metadata.targetGroups.NPM Scripts.4": [
      "apps/gateway/package.json",
      "nx/core/package-json"
    ],
    "metadata.targetGroups.NPM Scripts.5": [
      "apps/gateway/package.json",
      "nx/core/package-json"
    ],
    "metadata.targetGroups.NPM Scripts.6": [
      "apps/gateway/package.json",
      "nx/core/package-json"
    ],
    "metadata.targetGroups.NPM Scripts.7": [
      "apps/gateway/package.json",
      "nx/core/package-json"
    ],
    "metadata.targetGroups.NPM Scripts.8": [
      "apps/gateway/package.json",
      "nx/core/package-json"
    ],
    "metadata.targetGroups.NPM Scripts.9": [
      "apps/gateway/package.json",
      "nx/core/package-json"
    ],
    "metadata.targetGroups.NPM Scripts.10": [
      "apps/gateway/package.json",
      "nx/core/package-json"
    ],
    "metadata.targetGroups.NPM Scripts.11": [
      "apps/gateway/package.json",
      "nx/core/package-json"
    ],
    "metadata.js": [
      "apps/gateway/package.json",
      "nx/core/package-json"
    ],
    "metadata.js.packageName": [
      "apps/gateway/package.json",
      "nx/core/package-json"
    ],
    "metadata.js.packageVersion": [
      "apps/gateway/package.json",
      "nx/core/package-json"
    ],
    "metadata.js.isInPackageManagerWorkspaces": [
      "apps/gateway/package.json",
      "nx/core/package-json"
    ],
    "targets.clean": [
      "apps/gateway/package.json",
      "nx/core/package-json"
    ],
    "targets.clean.executor": [
      "apps/gateway/package.json",
      "nx/core/package-json"
    ],
    "targets.clean.options": [
      "apps/gateway/package.json",
      "nx/core/package-json"
    ],
    "targets.clean.metadata": [
      "apps/gateway/package.json",
      "nx/core/package-json"
    ],
    "targets.clean.options.script": [
      "apps/gateway/package.json",
      "nx/core/package-json"
    ],
    "targets.clean.metadata.scriptContent": [
      "apps/gateway/package.json",
      "nx/core/package-json"
    ],
    "targets.clean.metadata.runCommand": [
      "apps/gateway/package.json",
      "nx/core/package-json"
    ],
    "targets.prebuild": [
      "apps/gateway/package.json",
      "nx/core/package-json"
    ],
    "targets.prebuild.executor": [
      "apps/gateway/package.json",
      "nx/core/package-json"
    ],
    "targets.prebuild.options": [
      "apps/gateway/package.json",
      "nx/core/package-json"
    ],
    "targets.prebuild.metadata": [
      "apps/gateway/package.json",
      "nx/core/package-json"
    ],
    "targets.prebuild.options.script": [
      "apps/gateway/package.json",
      "nx/core/package-json"
    ],
    "targets.prebuild.metadata.scriptContent": [
      "apps/gateway/package.json",
      "nx/core/package-json"
    ],
    "targets.prebuild.metadata.runCommand": [
      "apps/gateway/package.json",
      "nx/core/package-json"
    ],
    "targets.build": [
      "apps/gateway/package.json",
      "nx/core/package-json"
    ],
    "targets.build.executor": [
      "apps/gateway/package.json",
      "nx/core/package-json"
    ],
    "targets.build.options": [
      "apps/gateway/package.json",
      "nx/core/package-json"
    ],
    "targets.build.metadata": [
      "apps/gateway/package.json",
      "nx/core/package-json"
    ],
    "targets.build.options.script": [
      "apps/gateway/package.json",
      "nx/core/package-json"
    ],
    "targets.build.metadata.scriptContent": [
      "apps/gateway/package.json",
      "nx/core/package-json"
    ],
    "targets.build.metadata.runCommand": [
      "apps/gateway/package.json",
      "nx/core/package-json"
    ],
    "targets.start": [
      "apps/gateway/package.json",
      "nx/core/package-json"
    ],
    "targets.start.executor": [
      "apps/gateway/package.json",
      "nx/core/package-json"
    ],
    "targets.start.options": [
      "apps/gateway/package.json",
      "nx/core/package-json"
    ],
    "targets.start.metadata": [
      "apps/gateway/package.json",
      "nx/core/package-json"
    ],
    "targets.start.options.script": [
      "apps/gateway/package.json",
      "nx/core/package-json"
    ],
    "targets.start.metadata.scriptContent": [
      "apps/gateway/package.json",
      "nx/core/package-json"
    ],
    "targets.start.metadata.runCommand": [
      "apps/gateway/package.json",
      "nx/core/package-json"
    ],
    "targets.start:dev": [
      "apps/gateway/package.json",
      "nx/core/package-json"
    ],
    "targets.start:dev.executor": [
      "apps/gateway/package.json",
      "nx/core/package-json"
    ],
    "targets.start:dev.options": [
      "apps/gateway/package.json",
      "nx/core/package-json"
    ],
    "targets.start:dev.metadata": [
      "apps/gateway/package.json",
      "nx/core/package-json"
    ],
    "targets.start:dev.options.script": [
      "apps/gateway/package.json",
      "nx/core/package-json"
    ],
    "targets.start:dev.metadata.scriptContent": [
      "apps/gateway/package.json",
      "nx/core/package-json"
    ],
    "targets.start:dev.metadata.runCommand": [
      "apps/gateway/package.json",
      "nx/core/package-json"
    ],
    "targets.start:watch": [
      "apps/gateway/package.json",
      "nx/core/package-json"
    ],
    "targets.start:watch.executor": [
      "apps/gateway/package.json",
      "nx/core/package-json"
    ],
    "targets.start:watch.options": [
      "apps/gateway/package.json",
      "nx/core/package-json"
    ],
    "targets.start:watch.metadata": [
      "apps/gateway/package.json",
      "nx/core/package-json"
    ],
    "targets.start:watch.options.script": [
      "apps/gateway/package.json",
      "nx/core/package-json"
    ],
    "targets.start:watch.metadata.scriptContent": [
      "apps/gateway/package.json",
      "nx/core/package-json"
    ],
    "targets.start:watch.metadata.runCommand": [
      "apps/gateway/package.json",
      "nx/core/package-json"
    ],
    "targets.start:debug": [
      "apps/gateway/package.json",
      "nx/core/package-json"
    ],
    "targets.start:debug.executor": [
      "apps/gateway/package.json",
      "nx/core/package-json"
    ],
    "targets.start:debug.options": [
      "apps/gateway/package.json",
      "nx/core/package-json"
    ],
    "targets.start:debug.metadata": [
      "apps/gateway/package.json",
      "nx/core/package-json"
    ],
    "targets.start:debug.options.script": [
      "apps/gateway/package.json",
      "nx/core/package-json"
    ],
    "targets.start:debug.metadata.scriptContent": [
      "apps/gateway/package.json",
      "nx/core/package-json"
    ],
    "targets.start:debug.metadata.runCommand": [
      "apps/gateway/package.json",
      "nx/core/package-json"
    ],
    "targets.start:prod": [
      "apps/gateway/package.json",
      "nx/core/package-json"
    ],
    "targets.start:prod.executor": [
      "apps/gateway/package.json",
      "nx/core/package-json"
    ],
    "targets.start:prod.options": [
      "apps/gateway/package.json",
      "nx/core/package-json"
    ],
    "targets.start:prod.metadata": [
      "apps/gateway/package.json",
      "nx/core/package-json"
    ],
    "targets.start:prod.options.script": [
      "apps/gateway/package.json",
      "nx/core/package-json"
    ],
    "targets.start:prod.metadata.scriptContent": [
      "apps/gateway/package.json",
      "nx/core/package-json"
    ],
    "targets.start:prod.metadata.runCommand": [
      "apps/gateway/package.json",
      "nx/core/package-json"
    ],
    "targets.test": [
      "apps/gateway/package.json",
      "nx/core/package-json"
    ],
    "targets.test.executor": [
      "apps/gateway/package.json",
      "nx/core/package-json"
    ],
    "targets.test.options": [
      "apps/gateway/package.json",
      "nx/core/package-json"
    ],
    "targets.test.metadata": [
      "apps/gateway/package.json",
      "nx/core/package-json"
    ],
    "targets.test.options.script": [
      "apps/gateway/package.json",
      "nx/core/package-json"
    ],
    "targets.test.metadata.scriptContent": [
      "apps/gateway/package.json",
      "nx/core/package-json"
    ],
    "targets.test.metadata.runCommand": [
      "apps/gateway/package.json",
      "nx/core/package-json"
    ],
    "targets.test:watch": [
      "apps/gateway/package.json",
      "nx/core/package-json"
    ],
    "targets.test:watch.executor": [
      "apps/gateway/package.json",
      "nx/core/package-json"
    ],
    "targets.test:watch.options": [
      "apps/gateway/package.json",
      "nx/core/package-json"
    ],
    "targets.test:watch.metadata": [
      "apps/gateway/package.json",
      "nx/core/package-json"
    ],
    "targets.test:watch.options.script": [
      "apps/gateway/package.json",
      "nx/core/package-json"
    ],
    "targets.test:watch.metadata.scriptContent": [
      "apps/gateway/package.json",
      "nx/core/package-json"
    ],
    "targets.test:watch.metadata.runCommand": [
      "apps/gateway/package.json",
      "nx/core/package-json"
    ],
    "targets.test:cov": [
      "apps/gateway/package.json",
      "nx/core/package-json"
    ],
    "targets.test:cov.executor": [
      "apps/gateway/package.json",
      "nx/core/package-json"
    ],
    "targets.test:cov.options": [
      "apps/gateway/package.json",
      "nx/core/package-json"
    ],
    "targets.test:cov.metadata": [
      "apps/gateway/package.json",
      "nx/core/package-json"
    ],
    "targets.test:cov.options.script": [
      "apps/gateway/package.json",
      "nx/core/package-json"
    ],
    "targets.test:cov.metadata.scriptContent": [
      "apps/gateway/package.json",
      "nx/core/package-json"
    ],
    "targets.test:cov.metadata.runCommand": [
      "apps/gateway/package.json",
      "nx/core/package-json"
    ],
    "targets.lint": [
      "apps/gateway/package.json",
      "nx/core/package-json"
    ],
    "targets.lint.executor": [
      "apps/gateway/package.json",
      "nx/core/package-json"
    ],
    "targets.lint.options": [
      "apps/gateway/package.json",
      "nx/core/package-json"
    ],
    "targets.lint.metadata": [
      "apps/gateway/package.json",
      "nx/core/package-json"
    ],
    "targets.lint.options.script": [
      "apps/gateway/package.json",
      "nx/core/package-json"
    ],
    "targets.lint.metadata.scriptContent": [
      "apps/gateway/package.json",
      "nx/core/package-json"
    ],
    "targets.lint.metadata.runCommand": [
      "apps/gateway/package.json",
      "nx/core/package-json"
    ]
  },
  "apps/gateway-api-e2e": {
    "root": [
      "apps/gateway-api-e2e/project.json",
      "nx/core/project-json"
    ],
    "targets": [
      "apps/gateway-api-e2e/eslint.config.mjs",
      "@nx/eslint/plugin"
    ],
    "targets.eslint:lint": [
      "apps/gateway-api-e2e/eslint.config.mjs",
      "@nx/eslint/plugin"
    ],
    "targets.eslint:lint.cache": [
      "apps/gateway-api-e2e/eslint.config.mjs",
      "@nx/eslint/plugin"
    ],
    "targets.eslint:lint.options": [
      "apps/gateway-api-e2e/eslint.config.mjs",
      "@nx/eslint/plugin"
    ],
    "targets.eslint:lint.inputs": [
      "apps/gateway-api-e2e/eslint.config.mjs",
      "@nx/eslint/plugin"
    ],
    "targets.eslint:lint.outputs": [
      "apps/gateway-api-e2e/eslint.config.mjs",
      "@nx/eslint/plugin"
    ],
    "targets.eslint:lint.metadata": [
      "apps/gateway-api-e2e/eslint.config.mjs",
      "@nx/eslint/plugin"
    ],
    "targets.eslint:lint.executor": [
      "apps/gateway-api-e2e/eslint.config.mjs",
      "@nx/eslint/plugin"
    ],
    "targets.eslint:lint.options.cwd": [
      "apps/gateway-api-e2e/eslint.config.mjs",
      "@nx/eslint/plugin"
    ],
    "targets.eslint:lint.options.command": [
      "apps/gateway-api-e2e/eslint.config.mjs",
      "@nx/eslint/plugin"
    ],
    "targets.eslint:lint.metadata.technologies": [
      "apps/gateway-api-e2e/eslint.config.mjs",
      "@nx/eslint/plugin"
    ],
    "targets.eslint:lint.metadata.technologies.0": [
      "apps/gateway-api-e2e/eslint.config.mjs",
      "@nx/eslint/plugin"
    ],
    "targets.eslint:lint.metadata.description": [
      "apps/gateway-api-e2e/eslint.config.mjs",
      "@nx/eslint/plugin"
    ],
    "targets.eslint:lint.metadata.help": [
      "apps/gateway-api-e2e/eslint.config.mjs",
      "@nx/eslint/plugin"
    ],
    "targets.eslint:lint.metadata.help.command": [
      "apps/gateway-api-e2e/eslint.config.mjs",
      "@nx/eslint/plugin"
    ],
    "targets.eslint:lint.metadata.help.example": [
      "apps/gateway-api-e2e/eslint.config.mjs",
      "@nx/eslint/plugin"
    ],
    "name": [
      "apps/gateway-api-e2e/project.json",
      "nx/core/project-json"
    ],
    "$schema": [
      "apps/gateway-api-e2e/project.json",
      "nx/core/project-json"
    ],
    "projectType": [
      "apps/gateway-api-e2e/project.json",
      "nx/core/project-json"
    ],
    "implicitDependencies": [
      "apps/gateway-api-e2e/project.json",
      "nx/core/project-json"
    ],
    "implicitDependencies.gateway-api": [
      "apps/gateway-api-e2e/project.json",
      "nx/core/project-json"
    ],
    "targets.e2e": [
      "apps/gateway-api-e2e/project.json",
      "nx/core/project-json"
    ],
    "targets.e2e.executor": [
      "apps/gateway-api-e2e/project.json",
      "nx/core/project-json"
    ],
    "targets.e2e.outputs": [
      "apps/gateway-api-e2e/project.json",
      "nx/core/project-json"
    ],
    "targets.e2e.options": [
      "apps/gateway-api-e2e/project.json",
      "nx/core/project-json"
    ],
    "targets.e2e.dependsOn": [
      "apps/gateway-api-e2e/project.json",
      "nx/core/project-json"
    ],
    "targets.e2e.options.jestConfig": [
      "apps/gateway-api-e2e/project.json",
      "nx/core/project-json"
    ],
    "targets.e2e.options.passWithNoTests": [
      "apps/gateway-api-e2e/project.json",
      "nx/core/project-json"
    ]
  },
  "apps/whatsapp-microservice-e2e": {
    "root": [
      "apps/whatsapp-microservice-e2e/project.json",
      "nx/core/project-json"
    ],
    "targets": [
      "eslint.config.mjs",
      "@nx/eslint/plugin"
    ],
    "targets.eslint:lint": [
      "eslint.config.mjs",
      "@nx/eslint/plugin"
    ],
    "targets.eslint:lint.cache": [
      "eslint.config.mjs",
      "@nx/eslint/plugin"
    ],
    "targets.eslint:lint.options": [
      "eslint.config.mjs",
      "@nx/eslint/plugin"
    ],
    "targets.eslint:lint.inputs": [
      "eslint.config.mjs",
      "@nx/eslint/plugin"
    ],
    "targets.eslint:lint.outputs": [
      "eslint.config.mjs",
      "@nx/eslint/plugin"
    ],
    "targets.eslint:lint.metadata": [
      "eslint.config.mjs",
      "@nx/eslint/plugin"
    ],
    "targets.eslint:lint.executor": [
      "eslint.config.mjs",
      "@nx/eslint/plugin"
    ],
    "targets.eslint:lint.options.cwd": [
      "eslint.config.mjs",
      "@nx/eslint/plugin"
    ],
    "targets.eslint:lint.options.command": [
      "eslint.config.mjs",
      "@nx/eslint/plugin"
    ],
    "targets.eslint:lint.metadata.technologies": [
      "eslint.config.mjs",
      "@nx/eslint/plugin"
    ],
    "targets.eslint:lint.metadata.technologies.0": [
      "eslint.config.mjs",
      "@nx/eslint/plugin"
    ],
    "targets.eslint:lint.metadata.description": [
      "eslint.config.mjs",
      "@nx/eslint/plugin"
    ],
    "targets.eslint:lint.metadata.help": [
      "eslint.config.mjs",
      "@nx/eslint/plugin"
    ],
    "targets.eslint:lint.metadata.help.command": [
      "eslint.config.mjs",
      "@nx/eslint/plugin"
    ],
    "targets.eslint:lint.metadata.help.example": [
      "eslint.config.mjs",
      "@nx/eslint/plugin"
    ],
    "name": [
      "apps/whatsapp-microservice-e2e/project.json",
      "nx/core/project-json"
    ],
    "$schema": [
      "apps/whatsapp-microservice-e2e/project.json",
      "nx/core/project-json"
    ],
    "projectType": [
      "apps/whatsapp-microservice-e2e/project.json",
      "nx/core/project-json"
    ],
    "implicitDependencies": [
      "apps/whatsapp-microservice-e2e/project.json",
      "nx/core/project-json"
    ],
    "implicitDependencies.whatsapp-microservice": [
      "apps/whatsapp-microservice-e2e/project.json",
      "nx/core/project-json"
    ],
    "targets.e2e": [
      "apps/whatsapp-microservice-e2e/project.json",
      "nx/core/project-json"
    ],
    "targets.e2e.executor": [
      "apps/whatsapp-microservice-e2e/project.json",
      "nx/core/project-json"
    ],
    "targets.e2e.outputs": [
      "apps/whatsapp-microservice-e2e/project.json",
      "nx/core/project-json"
    ],
    "targets.e2e.options": [
      "apps/whatsapp-microservice-e2e/project.json",
      "nx/core/project-json"
    ],
    "targets.e2e.dependsOn": [
      "apps/whatsapp-microservice-e2e/project.json",
      "nx/core/project-json"
    ],
    "targets.e2e.options.jestConfig": [
      "apps/whatsapp-microservice-e2e/project.json",
      "nx/core/project-json"
    ],
    "targets.e2e.options.passWithNoTests": [
      "apps/whatsapp-microservice-e2e/project.json",
      "nx/core/project-json"
    ]
  },
  "packages/database": {
    "root": [
      "packages/database/package.json",
      "nx/core/package-json"
    ],
    "targets": [
      "eslint.config.mjs",
      "@nx/eslint/plugin"
    ],
    "targets.eslint:lint": [
      "eslint.config.mjs",
      "@nx/eslint/plugin"
    ],
    "targets.eslint:lint.cache": [
      "eslint.config.mjs",
      "@nx/eslint/plugin"
    ],
    "targets.eslint:lint.options": [
      "eslint.config.mjs",
      "@nx/eslint/plugin"
    ],
    "targets.eslint:lint.inputs": [
      "eslint.config.mjs",
      "@nx/eslint/plugin"
    ],
    "targets.eslint:lint.outputs": [
      "eslint.config.mjs",
      "@nx/eslint/plugin"
    ],
    "targets.eslint:lint.metadata": [
      "eslint.config.mjs",
      "@nx/eslint/plugin"
    ],
    "targets.eslint:lint.executor": [
      "eslint.config.mjs",
      "@nx/eslint/plugin"
    ],
    "targets.eslint:lint.options.cwd": [
      "eslint.config.mjs",
      "@nx/eslint/plugin"
    ],
    "targets.eslint:lint.options.command": [
      "eslint.config.mjs",
      "@nx/eslint/plugin"
    ],
    "targets.eslint:lint.metadata.technologies": [
      "eslint.config.mjs",
      "@nx/eslint/plugin"
    ],
    "targets.eslint:lint.metadata.technologies.0": [
      "eslint.config.mjs",
      "@nx/eslint/plugin"
    ],
    "targets.eslint:lint.metadata.description": [
      "eslint.config.mjs",
      "@nx/eslint/plugin"
    ],
    "targets.eslint:lint.metadata.help": [
      "eslint.config.mjs",
      "@nx/eslint/plugin"
    ],
    "targets.eslint:lint.metadata.help.command": [
      "eslint.config.mjs",
      "@nx/eslint/plugin"
    ],
    "targets.eslint:lint.metadata.help.example": [
      "eslint.config.mjs",
      "@nx/eslint/plugin"
    ],
    "name": [
      "packages/database/package.json",
      "nx/core/package-json"
    ],
    "tags": [
      "packages/database/package.json",
      "nx/core/package-json"
    ],
    "tags.npm:public": [
      "packages/database/package.json",
      "nx/core/package-json"
    ],
    "metadata.targetGroups": [
      "packages/database/package.json",
      "nx/core/package-json"
    ],
    "metadata.targetGroups.NPM Scripts": [
      "packages/database/package.json",
      "nx/core/package-json"
    ],
    "metadata.targetGroups.NPM Scripts.0": [
      "packages/database/package.json",
      "nx/core/package-json"
    ],
    "metadata.targetGroups.NPM Scripts.1": [
      "packages/database/package.json",
      "nx/core/package-json"
    ],
    "metadata.targetGroups.NPM Scripts.2": [
      "packages/database/package.json",
      "nx/core/package-json"
    ],
    "metadata.targetGroups.NPM Scripts.3": [
      "packages/database/package.json",
      "nx/core/package-json"
    ],
    "metadata.targetGroups.NPM Scripts.4": [
      "packages/database/package.json",
      "nx/core/package-json"
    ],
    "metadata.targetGroups.NPM Scripts.5": [
      "packages/database/package.json",
      "nx/core/package-json"
    ],
    "metadata.targetGroups.NPM Scripts.6": [
      "packages/database/package.json",
      "nx/core/package-json"
    ],
    "metadata.targetGroups.NPM Scripts.7": [
      "packages/database/package.json",
      "nx/core/package-json"
    ],
    "metadata.targetGroups.NPM Scripts.8": [
      "packages/database/package.json",
      "nx/core/package-json"
    ],
    "metadata.targetGroups.NPM Scripts.9": [
      "packages/database/package.json",
      "nx/core/package-json"
    ],
    "metadata.targetGroups.NPM Scripts.10": [
      "packages/database/package.json",
      "nx/core/package-json"
    ],
    "metadata.js": [
      "packages/database/package.json",
      "nx/core/package-json"
    ],
    "metadata.js.packageName": [
      "packages/database/package.json",
      "nx/core/package-json"
    ],
    "metadata.js.packageVersion": [
      "packages/database/package.json",
      "nx/core/package-json"
    ],
    "metadata.js.packageMain": [
      "packages/database/package.json",
      "nx/core/package-json"
    ],
    "metadata.js.isInPackageManagerWorkspaces": [
      "packages/database/package.json",
      "nx/core/package-json"
    ],
    "targets.clean": [
      "packages/database/package.json",
      "nx/core/package-json"
    ],
    "targets.clean.executor": [
      "packages/database/package.json",
      "nx/core/package-json"
    ],
    "targets.clean.options": [
      "packages/database/package.json",
      "nx/core/package-json"
    ],
    "targets.clean.metadata": [
      "packages/database/package.json",
      "nx/core/package-json"
    ],
    "targets.clean.options.script": [
      "packages/database/package.json",
      "nx/core/package-json"
    ],
    "targets.clean.metadata.scriptContent": [
      "packages/database/package.json",
      "nx/core/package-json"
    ],
    "targets.clean.metadata.runCommand": [
      "packages/database/package.json",
      "nx/core/package-json"
    ],
    "targets.prebuild": [
      "packages/database/package.json",
      "nx/core/package-json"
    ],
    "targets.prebuild.executor": [
      "packages/database/package.json",
      "nx/core/package-json"
    ],
    "targets.prebuild.options": [
      "packages/database/package.json",
      "nx/core/package-json"
    ],
    "targets.prebuild.metadata": [
      "packages/database/package.json",
      "nx/core/package-json"
    ],
    "targets.prebuild.options.script": [
      "packages/database/package.json",
      "nx/core/package-json"
    ],
    "targets.prebuild.metadata.scriptContent": [
      "packages/database/package.json",
      "nx/core/package-json"
    ],
    "targets.prebuild.metadata.runCommand": [
      "packages/database/package.json",
      "nx/core/package-json"
    ],
    "targets.build": [
      "packages/database/package.json",
      "nx/core/package-json"
    ],
    "targets.build.executor": [
      "packages/database/package.json",
      "nx/core/package-json"
    ],
    "targets.build.options": [
      "packages/database/package.json",
      "nx/core/package-json"
    ],
    "targets.build.metadata": [
      "packages/database/package.json",
      "nx/core/package-json"
    ],
    "targets.build.options.script": [
      "packages/database/package.json",
      "nx/core/package-json"
    ],
    "targets.build.metadata.scriptContent": [
      "packages/database/package.json",
      "nx/core/package-json"
    ],
    "targets.build.metadata.runCommand": [
      "packages/database/package.json",
      "nx/core/package-json"
    ],
    "targets.generate": [
      "packages/database/package.json",
      "nx/core/package-json"
    ],
    "targets.generate.executor": [
      "packages/database/package.json",
      "nx/core/package-json"
    ],
    "targets.generate.options": [
      "packages/database/package.json",
      "nx/core/package-json"
    ],
    "targets.generate.metadata": [
      "packages/database/package.json",
      "nx/core/package-json"
    ],
    "targets.generate.options.script": [
      "packages/database/package.json",
      "nx/core/package-json"
    ],
    "targets.generate.metadata.scriptContent": [
      "packages/database/package.json",
      "nx/core/package-json"
    ],
    "targets.generate.metadata.runCommand": [
      "packages/database/package.json",
      "nx/core/package-json"
    ],
    "targets.migrate:dev": [
      "packages/database/package.json",
      "nx/core/package-json"
    ],
    "targets.migrate:dev.executor": [
      "packages/database/package.json",
      "nx/core/package-json"
    ],
    "targets.migrate:dev.options": [
      "packages/database/package.json",
      "nx/core/package-json"
    ],
    "targets.migrate:dev.metadata": [
      "packages/database/package.json",
      "nx/core/package-json"
    ],
    "targets.migrate:dev.options.script": [
      "packages/database/package.json",
      "nx/core/package-json"
    ],
    "targets.migrate:dev.metadata.scriptContent": [
      "packages/database/package.json",
      "nx/core/package-json"
    ],
    "targets.migrate:dev.metadata.runCommand": [
      "packages/database/package.json",
      "nx/core/package-json"
    ],
    "targets.migrate:deploy": [
      "packages/database/package.json",
      "nx/core/package-json"
    ],
    "targets.migrate:deploy.executor": [
      "packages/database/package.json",
      "nx/core/package-json"
    ],
    "targets.migrate:deploy.options": [
      "packages/database/package.json",
      "nx/core/package-json"
    ],
    "targets.migrate:deploy.metadata": [
      "packages/database/package.json",
      "nx/core/package-json"
    ],
    "targets.migrate:deploy.options.script": [
      "packages/database/package.json",
      "nx/core/package-json"
    ],
    "targets.migrate:deploy.metadata.scriptContent": [
      "packages/database/package.json",
      "nx/core/package-json"
    ],
    "targets.migrate:deploy.metadata.runCommand": [
      "packages/database/package.json",
      "nx/core/package-json"
    ],
    "targets.migrate:reset": [
      "packages/database/package.json",
      "nx/core/package-json"
    ],
    "targets.migrate:reset.executor": [
      "packages/database/package.json",
      "nx/core/package-json"
    ],
    "targets.migrate:reset.options": [
      "packages/database/package.json",
      "nx/core/package-json"
    ],
    "targets.migrate:reset.metadata": [
      "packages/database/package.json",
      "nx/core/package-json"
    ],
    "targets.migrate:reset.options.script": [
      "packages/database/package.json",
      "nx/core/package-json"
    ],
    "targets.migrate:reset.metadata.scriptContent": [
      "packages/database/package.json",
      "nx/core/package-json"
    ],
    "targets.migrate:reset.metadata.runCommand": [
      "packages/database/package.json",
      "nx/core/package-json"
    ],
    "targets.studio": [
      "packages/database/package.json",
      "nx/core/package-json"
    ],
    "targets.studio.executor": [
      "packages/database/package.json",
      "nx/core/package-json"
    ],
    "targets.studio.options": [
      "packages/database/package.json",
      "nx/core/package-json"
    ],
    "targets.studio.metadata": [
      "packages/database/package.json",
      "nx/core/package-json"
    ],
    "targets.studio.options.script": [
      "packages/database/package.json",
      "nx/core/package-json"
    ],
    "targets.studio.metadata.scriptContent": [
      "packages/database/package.json",
      "nx/core/package-json"
    ],
    "targets.studio.metadata.runCommand": [
      "packages/database/package.json",
      "nx/core/package-json"
    ],
    "targets.seed": [
      "packages/database/package.json",
      "nx/core/package-json"
    ],
    "targets.seed.executor": [
      "packages/database/package.json",
      "nx/core/package-json"
    ],
    "targets.seed.options": [
      "packages/database/package.json",
      "nx/core/package-json"
    ],
    "targets.seed.metadata": [
      "packages/database/package.json",
      "nx/core/package-json"
    ],
    "targets.seed.options.script": [
      "packages/database/package.json",
      "nx/core/package-json"
    ],
    "targets.seed.metadata.scriptContent": [
      "packages/database/package.json",
      "nx/core/package-json"
    ],
    "targets.seed.metadata.runCommand": [
      "packages/database/package.json",
      "nx/core/package-json"
    ],
    "targets.db:push": [
      "packages/database/package.json",
      "nx/core/package-json"
    ],
    "targets.db:push.executor": [
      "packages/database/package.json",
      "nx/core/package-json"
    ],
    "targets.db:push.options": [
      "packages/database/package.json",
      "nx/core/package-json"
    ],
    "targets.db:push.metadata": [
      "packages/database/package.json",
      "nx/core/package-json"
    ],
    "targets.db:push.options.script": [
      "packages/database/package.json",
      "nx/core/package-json"
    ],
    "targets.db:push.metadata.scriptContent": [
      "packages/database/package.json",
      "nx/core/package-json"
    ],
    "targets.db:push.metadata.runCommand": [
      "packages/database/package.json",
      "nx/core/package-json"
    ],
    "targets.db:pull": [
      "packages/database/package.json",
      "nx/core/package-json"
    ],
    "targets.db:pull.executor": [
      "packages/database/package.json",
      "nx/core/package-json"
    ],
    "targets.db:pull.options": [
      "packages/database/package.json",
      "nx/core/package-json"
    ],
    "targets.db:pull.metadata": [
      "packages/database/package.json",
      "nx/core/package-json"
    ],
    "targets.db:pull.options.script": [
      "packages/database/package.json",
      "nx/core/package-json"
    ],
    "targets.db:pull.metadata.scriptContent": [
      "packages/database/package.json",
      "nx/core/package-json"
    ],
    "targets.db:pull.metadata.runCommand": [
      "packages/database/package.json",
      "nx/core/package-json"
    ],
    "targets.nx-release-publish": [
      "packages/database/package.json",
      "nx/core/package-json"
    ],
    "targets.nx-release-publish.executor": [
      "packages/database/package.json",
      "nx/core/package-json"
    ],
    "targets.nx-release-publish.dependsOn": [
      "packages/database/package.json",
      "nx/core/package-json"
    ],
    "targets.nx-release-publish.options": [
      "packages/database/package.json",
      "nx/core/package-json"
    ]
  },
  "apps/whatsapp-service": {
    "root": [
      "apps/whatsapp-service/package.json",
      "nx/core/package-json"
    ],
    "name": [
      "apps/whatsapp-service/package.json",
      "nx/core/package-json"
    ],
    "tags": [
      "apps/whatsapp-service/package.json",
      "nx/core/package-json"
    ],
    "tags.npm:public": [
      "apps/whatsapp-service/package.json",
      "nx/core/package-json"
    ],
    "metadata.targetGroups": [
      "apps/whatsapp-service/package.json",
      "nx/core/package-json"
    ],
    "metadata.targetGroups.NPM Scripts": [
      "apps/whatsapp-service/package.json",
      "nx/core/package-json"
    ],
    "metadata.targetGroups.NPM Scripts.0": [
      "apps/whatsapp-service/package.json",
      "nx/core/package-json"
    ],
    "metadata.targetGroups.NPM Scripts.1": [
      "apps/whatsapp-service/package.json",
      "nx/core/package-json"
    ],
    "metadata.targetGroups.NPM Scripts.2": [
      "apps/whatsapp-service/package.json",
      "nx/core/package-json"
    ],
    "metadata.js": [
      "apps/whatsapp-service/package.json",
      "nx/core/package-json"
    ],
    "metadata.js.packageName": [
      "apps/whatsapp-service/package.json",
      "nx/core/package-json"
    ],
    "metadata.js.packageVersion": [
      "apps/whatsapp-service/package.json",
      "nx/core/package-json"
    ],
    "metadata.js.isInPackageManagerWorkspaces": [
      "apps/whatsapp-service/package.json",
      "nx/core/package-json"
    ],
    "targets": [
      "apps/whatsapp-service/package.json",
      "nx/core/package-json"
    ],
    "targets.dev": [
      "apps/whatsapp-service/package.json",
      "nx/core/package-json"
    ],
    "targets.dev.executor": [
      "apps/whatsapp-service/package.json",
      "nx/core/package-json"
    ],
    "targets.dev.options": [
      "apps/whatsapp-service/package.json",
      "nx/core/package-json"
    ],
    "targets.dev.metadata": [
      "apps/whatsapp-service/package.json",
      "nx/core/package-json"
    ],
    "targets.dev.options.script": [
      "apps/whatsapp-service/package.json",
      "nx/core/package-json"
    ],
    "targets.dev.metadata.scriptContent": [
      "apps/whatsapp-service/package.json",
      "nx/core/package-json"
    ],
    "targets.dev.metadata.runCommand": [
      "apps/whatsapp-service/package.json",
      "nx/core/package-json"
    ],
    "targets.build": [
      "apps/whatsapp-service/package.json",
      "nx/core/package-json"
    ],
    "targets.build.executor": [
      "apps/whatsapp-service/package.json",
      "nx/core/package-json"
    ],
    "targets.build.options": [
      "apps/whatsapp-service/package.json",
      "nx/core/package-json"
    ],
    "targets.build.metadata": [
      "apps/whatsapp-service/package.json",
      "nx/core/package-json"
    ],
    "targets.build.options.script": [
      "apps/whatsapp-service/package.json",
      "nx/core/package-json"
    ],
    "targets.build.metadata.scriptContent": [
      "apps/whatsapp-service/package.json",
      "nx/core/package-json"
    ],
    "targets.build.metadata.runCommand": [
      "apps/whatsapp-service/package.json",
      "nx/core/package-json"
    ],
    "targets.start": [
      "apps/whatsapp-service/package.json",
      "nx/core/package-json"
    ],
    "targets.start.executor": [
      "apps/whatsapp-service/package.json",
      "nx/core/package-json"
    ],
    "targets.start.options": [
      "apps/whatsapp-service/package.json",
      "nx/core/package-json"
    ],
    "targets.start.metadata": [
      "apps/whatsapp-service/package.json",
      "nx/core/package-json"
    ],
    "targets.start.options.script": [
      "apps/whatsapp-service/package.json",
      "nx/core/package-json"
    ],
    "targets.start.metadata.scriptContent": [
      "apps/whatsapp-service/package.json",
      "nx/core/package-json"
    ],
    "targets.start.metadata.runCommand": [
      "apps/whatsapp-service/package.json",
      "nx/core/package-json"
    ],
    "targets.nx-release-publish": [
      "apps/whatsapp-service/package.json",
      "nx/core/package-json"
    ],
    "targets.nx-release-publish.executor": [
      "apps/whatsapp-service/package.json",
      "nx/core/package-json"
    ],
    "targets.nx-release-publish.dependsOn": [
      "apps/whatsapp-service/package.json",
      "nx/core/package-json"
    ],
    "targets.nx-release-publish.options": [
      "apps/whatsapp-service/package.json",
      "nx/core/package-json"
    ]
  }
}